metacase/__init__.py
metacase/adapter.py
metacase/adapters/__init__.py
metacase/adapters/polarion/__init__.py
metacase/adapters/polarion/args/__init__.py
metacase/adapters/polarion/args/polarion_args_parser.py
metacase/adapters/polarion/polarion_adapter.py
metacase/adapters/polarion/polarion_reporter.py
metacase/adapters/polarion/polarion_test_case.py
metacase/adapters/polarion/utils/__init__.py
metacase/adapters/polarion/utils/polarion_config.py
metacase/adapters/polarion/utils/polarion_xml.py
metacase/args/__init__.py
metacase/args/args_parser.py
metacase/connectors/__init__.py
metacase/connectors/jira/__init__.py
metacase/connectors/jira/jira_config.py
metacase/connectors/jira/jira_connector.py
metacase/metacase.py
metacase/schema/.fmf/version
metacase/schema/__init__.py
metacase/schema/adapter/main.fmf
metacase/schema/adapter/polarion/automated.fmf
metacase/schema/adapter/polarion/lookup-method.fmf
metacase/schema/adapter/polarion/main.fmf
metacase/schema/adapter/polarion/positive.fmf
metacase/schema/adapter/polarion/project.fmf
metacase/schema/adapter/polarion/subtypes.fmf
metacase/schema/approvals.fmf
metacase/schema/authors.fmf
metacase/schema/components.fmf
metacase/schema/defects/main.fmf
metacase/schema/description.fmf
metacase/schema/estimate.fmf
metacase/schema/importance.fmf
metacase/schema/level.fmf
metacase/schema/parameters.fmf
metacase/schema/properties.fmf
metacase/schema/requirements/main.fmf
metacase/schema/subcomponents.fmf
metacase/schema/summary.fmf
metacase/schema/tags.fmf
metacase/schema/test-steps.fmf
metacase/schema/testsuite/compatible-topologies.fmf
metacase/schema/testsuite/main.fmf
metacase/schema/testsuite/parameters.fmf
metacase/schema/testsuite/properties.fmf
metacase/schema/type.fmf
metacase/testcase.py
metacase-0.1.0.dist-info/entry_points.txt
metacase-0.1.0.dist-info/LICENSE
metacase-0.1.0.dist-info/WHEEL
metacase-0.1.0.dist-info/METADATA
metacase-0.1.0.dist-info/RECORD
