Metadata-Version: 2.1
Name: metacase
Version: 0.1.0
Summary: MetaCase is test case exporter tool based on FMF (Flexible Metadata Format) .
Home-page: https://github.com/enkeys/metacase/
License: Apache-2.0
Keywords: fmf,metadata,test,case,jira
Author: Fernando Giorgetti
Author-email: fgiorget@redhat.com
Maintainer: Dominik Lenoch
Maintainer-email: dlenoch@redhat.com
Requires-Python: >=3.9,<4.0
Classifier: License :: OSI Approved :: Apache Software License
Classifier: Programming Language :: Python :: 3
Classifier: Programming Language :: Python :: 3.10
Classifier: Programming Language :: Python :: 3.9
Provides-Extra: docs
Requires-Dist: fmf (>=1.1.0,<2.0.0)
Requires-Dist: jira (>=3.2.0,<4.0.0)
Requires-Dist: myst-parser (>=0.12.10,<0.13.0); extra == "docs"
Requires-Dist: requests (>=2.28.0,<3.0.0)
Requires-Dist: sphinx (>=3.5.4,<4.0.0); extra == "docs"
Requires-Dist: sphinx-autobuild (>=2020.9.1,<2021.0.0); extra == "docs"
Requires-Dist: sphinx-rtd-theme (>=0.5.2,<0.6.0); extra == "docs"
Requires-Dist: urllib3 (>=1.26.9,<2.0.0)
Project-URL: Repository, https://github.com/enkeys/metacase/
